mat73/__init__.py
mat73/core.py
mat73/version.py
mat73-0.65.dist-info/LICENSE
mat73-0.65.dist-info/METADATA
mat73-0.65.dist-info/WHEEL
mat73-0.65.dist-info/top_level.txt
mat73-0.65.dist-info/RECORD
