Metadata-Version: 2.1
Name: mat73
Version: 0.65
Summary: Load MATLAB .mat 7.3 into Python native data types (via h5/hd5/hdf5/h5py)
Home-page: https://github.com/skjerns/mat7.3
Download-URL: https://github.com/skjerns/mat7.3/archive/v0.65.tar.gz
Author: skjerns
Author-email: nomail@nomail.com
License: GPL3
Classifier: Programming Language :: Python :: 3
Classifier: License :: OSI Approved :: GNU General Public License v3 (GPLv3)
Classifier: Operating System :: OS Independent
License-File: LICENSE
